kynegoes_easy_dataflow/Download_Catastro_Spain.py
kynegoes_easy_dataflow/Kynegos_functions.py
kynegoes_easy_dataflow/__init__.py
kyne_goes_easy_dataflow-1.0.2.dist-info/LICENSE
kyne_goes_easy_dataflow-1.0.2.dist-info/METADATA
kyne_goes_easy_dataflow-1.0.2.dist-info/WHEEL
kyne_goes_easy_dataflow-1.0.2.dist-info/top_level.txt
kyne_goes_easy_dataflow-1.0.2.dist-info/RECORD
