Metadata-Version: 2.1
Name: kyne-goes-easy-dataflow
Version: 1.0.2
Summary: Automatización de procesos de Data para Kynegos
Home-page: https://gitlab.com/GabiAnt95/kynegoeasy-dataflow
Author: Kynegos - Capital Energy
Author-email: digital.data@capitalenergy.com
License: Kynegos License
Classifier: Programming Language :: Python :: 3
Classifier: License :: Other/Proprietary License
Classifier: Operating System :: OS Independent
Requires-Python: >=3.6
License-File: LICENSE
Requires-Dist: google-auth
Requires-Dist: google-cloud-bigquery
Requires-Dist: google-cloud-storage
Requires-Dist: google-cloud-aiplatform
Requires-Dist: pandas
Requires-Dist: atoma
Requires-Dist: gdal
